live11_api_fetch/__init__.py
live11_api_fetch/__main__.py
live11_api_fetch/server.py
live11_api_fetch-0.2.0.dist-info/METADATA
live11_api_fetch-0.2.0.dist-info/WHEEL
live11_api_fetch-0.2.0.dist-info/entry_points.txt
live11_api_fetch-0.2.0.dist-info/licenses/LICENSE
live11_api_fetch-0.2.0.dist-info/RECORD
