Metadata-Version: 2.4
Name: live11-api-fetch
Version: 0.2.0
Summary: A Model Context Protocol server to query Live 11 API documentation
License: MIT
License-File: LICENSE
Classifier: Development Status :: 4 - Beta
Classifier: Intended Audience :: Developers
Classifier: License :: OSI Approved :: MIT License
Classifier: Programming Language :: Python :: 3
Classifier: Programming Language :: Python :: 3.10
Requires-Python: >=3.10
Requires-Dist: build
Requires-Dist: httpx<0.28
Requires-Dist: mcp>=1.1.3
Requires-Dist: pydantic>=2.0.0
Requires-Dist: twine
